mimeco/__init__.py
mimeco/analysis.py
mimeco/enterocyte_specific_utils.py
mimeco/sandbox.py
mimeco/toy_example.py
mimeco/utils.py
mimeco/__pycache__/__init__.cpython-310.pyc
mimeco/__pycache__/__init__.cpython-313.pyc
mimeco/__pycache__/analysis.cpython-310.pyc
mimeco/__pycache__/enterocyte_specific_utils.cpython-310.pyc
mimeco/__pycache__/utils.cpython-310.pyc
mimeco/__pycache__/utils.cpython-313.pyc
mimeco/resources/AAD_BiGG.tsv
mimeco/resources/AAD_VMH.tsv
mimeco/resources/MIMEco_logo.png
mimeco/resources/Western_diet_BiGG.csv
mimeco/resources/Western_diet_VMH.csv
mimeco/resources/blood_reactions_id_enterocyte.csv
mimeco/resources/enterocyte_BiGG.xml
mimeco/resources/enterocyte_VMH.xml
mimeco/resources/enterocyte_VMH_v2.xml
mimeco/resources/enterocyte_VMH_v3.xml
mimeco-0.1.18.dist-info/licenses/LICENSE.md
mimeco-0.1.18.dist-info/METADATA
mimeco-0.1.18.dist-info/WHEEL
mimeco-0.1.18.dist-info/top_level.txt
mimeco-0.1.18.dist-info/RECORD
