Metadata-Version: 2.4
Name: mimeco
Version: 0.1.18
Summary: Multi-objective GEMs metabolic interaction inference
Author: Anna Lambert
Author-email: Anna LAMBERT <anna.lambert@univ-nantes.fr>
Keywords: GEMs,Multi-objective linear programming,bioinformatics,metabolic modelling,community modelling
Classifier: Programming Language :: Python :: 3
Classifier: License :: OSI Approved :: GNU General Public License v3 or later (GPLv3+)
Classifier: Operating System :: OS Independent
Requires-Python: >=3.10
License-File: LICENSE.md
Requires-Dist: pandas
Requires-Dist: cobra
Requires-Dist: scikit-learn
Requires-Dist: mocbapy
Requires-Dist: benpy
Requires-Dist: matplotlib
Dynamic: author
Dynamic: license-file
